pyadjoint/__init__.py
pyadjoint/adjoint_source.py
pyadjoint/config.py
pyadjoint/main.py
pyadjoint/adjoint_source_types/__init__.py
pyadjoint/adjoint_source_types/cc_traveltime_misfit.py
pyadjoint/adjoint_source_types/exponentiated_phase_misfit.py
pyadjoint/adjoint_source_types/multitaper_misfit.py
pyadjoint/adjoint_source_types/waveform_misfit.py
pyadjoint/tests/__init__.py
pyadjoint/tests/test_adjsrcs.py
pyadjoint/tests/test_config.py
pyadjoint/tests/test_utils.py
pyadjoint/utils/cctm.py
pyadjoint/utils/dpss.py
pyadjoint/utils/signal.py
pyadjoint-0.2.3.dist-info/licenses/LICENSE.txt
pyadjoint-0.2.3.dist-info/METADATA
pyadjoint-0.2.3.dist-info/WHEEL
pyadjoint-0.2.3.dist-info/top_level.txt
pyadjoint-0.2.3.dist-info/RECORD
