Metadata-Version: 2.4
Name: pyadjoint
Version: 0.2.3
Summary: Misfit measurement and adjoint source calculation
Author: adjTomo Dev Team
Author-email: adjtomo@gmail.com
License: Copyright (c) 2022, adjTomo Dev Team
Project-URL: homepage, https://github.com/adjtomo/
Project-URL: documentation, https://adjtomo.github.io/pyadjoint
Project-URL: repository, https://github.com/adjtomo/pyadjoint
Requires-Python: >=3.7
License-File: LICENSE.txt
Requires-Dist: obspy
Provides-Extra: test
Requires-Dist: pytest; extra == "test"
Provides-Extra: dev
Requires-Dist: pytest; extra == "dev"
Requires-Dist: flake8; extra == "dev"
Requires-Dist: nose; extra == "dev"
Provides-Extra: doc
Requires-Dist: fumo; extra == "doc"
Dynamic: license-file
